spectools/__init__.py
spectools/chebyshev/basis.py
spectools/chebyshev/basis_precise.py
spectools/chebyshev/chebyshev.py
spectools/fourier/transforms.py
spectools/helper/factorial.py
spectools/interpolation/interpolate.py
spectools/interpolation/interpolate_new.py
spectools/interpolation/interpolate_new_vectorized.py
spectools/interpolation/interpolate_single_t.py
spectools/interpolation/interpolate_single_t_vectorized.py
spectools/spherical/Yslm_full_vec.py
spectools/spherical/Yslm_mp.py
spectools/spherical/Yslm_prec_grid_mp.py
spectools/spherical/abstract.py
spectools/spherical/grids.py
spectools/spherical/swsh.py
spectools/spherical/transforms.py
spectools-2025.7.16.dist-info/METADATA
spectools-2025.7.16.dist-info/WHEEL
spectools-2025.7.16.dist-info/licenses/LICENSE
spectools-2025.7.16.dist-info/RECORD
