Metadata-Version: 2.4
Name: spectools
Version: 2025.7.16
Summary:  Numerical implementation of various spectral methods 
Project-URL: Homepage, https://gitlab.com/vaishakp/spectools
Project-URL: Bug Tracker, https://gitlab.com/vaishakp/spectools/issues
Author-email: Vaishak Prasad <vaishakprasad@gmail.com>
License-File: LICENSE
Classifier: License :: OSI Approved :: MIT License
Classifier: Operating System :: OS Independent
Classifier: Programming Language :: Python :: 3
Requires-Python: >=3.0
Requires-Dist: recommonmark
Requires-Dist: sphinx-rtd-theme
Requires-Dist: sxstools
Requires-Dist: waveformtools
Provides-Extra: opt
Requires-Dist: parallellib; extra == 'opt'
